consts
lyymoot
quotes
utils
