Metadata-Version: 2.1
Name: lyymoot
Version: 1.10
Summary: lyymoot for lyy
Author: yy
Author-email: 
License: MIT
License-File: LICENSE
